{
  "project_info": {
    "project_number": "161787640341",
    "firebase_url": "https://athenas-a7df8.firebaseio.com",
    "project_id": "athenas-a7df8",
    "storage_bucket": "athenas-a7df8.appspot.com"
  },
  "client": [
    {
      "client_info": {
        "mobilesdk_app_id": "1:161787640341:android:b156e68794fb2a0c",
        "android_client_info": {
          "package_name": "com.athenas.am.athenas"
        }
      },
      "oauth_client": [
        {
          "client_id": "161787640341-6dug506f4oab4rf186eo2rj0f786sd2i.apps.googleusercontent.com",
          "client_type": 1,
          "android_info": {
            "package_name": "com.athenas.am.athenas",
            "certificate_hash": "a89705668627d2ec83e5c79cbbe955aff55160ac"
          }
        },
        {
          "client_id": "161787640341-1o0lf7hm04j276e9cq8o62jr9h71dcme.apps.googleusercontent.com",
          "client_type": 3
        }
      ],
      "api_key": [
        {
          "current_key": "AIzaSyDELke8RB4CsO_lTGdV0rAh6s9rpzjHHnI"
        }
      ],
      "services": {
        "analytics_service": {
          "status": 1
        },
        "appinvite_service": {
          "status": 2,
          "other_platform_oauth_client": [
            {
              "client_id": "161787640341-1o0lf7hm04j276e9cq8o62jr9h71dcme.apps.googleusercontent.com",
              "client_type": 3
            }
          ]
        },
        "ads_service": {
          "status": 2
        }
      }
    }
  ],
  "configuration_version": "1"
}